frbcat/__init__.py
frbcat/__version__.py
frbcat/chime_repeaters.py
frbcat/frbcat_file.py
frbcat/misc.py
frbcat/tns.py
frbcat-0.2.21.dist-info/LICENSE
frbcat-0.2.21.dist-info/METADATA
frbcat-0.2.21.dist-info/WHEEL
frbcat-0.2.21.dist-info/top_level.txt
frbcat-0.2.21.dist-info/RECORD
