Metadata-Version: 2.1
Name: frbcat
Version: 0.2.21
Summary: Query the FRB catalogue
Home-page: http://github.com/davidgardenier/frbcat
Author: David Gardenier
Author-email: davidgardenier@gmail.com
License: MIT
Platform: UNKNOWN
Requires-Dist: pandas
Requires-Dist: requests
Requires-Dist: numpy
